django_sorting_bootstrap/__init__.py
django_sorting_bootstrap/locale/de/LC_MESSAGES/django.mo
django_sorting_bootstrap/locale/de/LC_MESSAGES/django.po
django_sorting_bootstrap/sort.py
django_sorting_bootstrap/templates/sorting_bootstrap/sort_headers_frag.html
django_sorting_bootstrap/templates/sorting_bootstrap/sort_link_frag.html
django_sorting_bootstrap/templates/sorting_bootstrap/sort_th_frag.html
django_sorting_bootstrap/templatetags/__init__.py
django_sorting_bootstrap/templatetags/sorting_tags.py
django_sorting_bootstrap/views.py
django_sorting_bootstrap-2.8.0.dist-info/LICENSE.rst
django_sorting_bootstrap-2.8.0.dist-info/WHEEL
django_sorting_bootstrap-2.8.0.dist-info/METADATA
django_sorting_bootstrap-2.8.0.dist-info/RECORD
