Metadata-Version: 2.1
Name: django-sorting-bootstrap
Version: 2.8.0
Summary: Sorting templates API using sorting, Django templatetags and Bootstrap classes.
Home-page: https://github.com/staticdev/django-sorting-bootstrap
License: MIT
Author: Thiago D'Ávila
Author-email: staticdev-support@protonmail.com
Requires-Python: >=3.7,<4.0
Classifier: Development Status :: 7 - Inactive
Classifier: Environment :: Web Environment
Classifier: Framework :: Django
Classifier: Intended Audience :: Developers
Classifier: License :: OSI Approved :: MIT License
Classifier: Operating System :: OS Independent
Classifier: Programming Language :: Python
Classifier: Programming Language :: Python :: 3
Classifier: Programming Language :: Python :: 3.10
Classifier: Programming Language :: Python :: 3.7
Classifier: Programming Language :: Python :: 3.8
Classifier: Programming Language :: Python :: 3.9
Classifier: Topic :: Internet :: WWW/HTTP
Classifier: Topic :: Internet :: WWW/HTTP :: Dynamic Content
Classifier: Topic :: Software Development :: Libraries :: Python Modules
Requires-Dist: django (>=2.0)
Project-URL: Changelog, https://github.com/staticdev/django-sorting-bootstrap/releases
Project-URL: Documentation, https://django-sorting-bootstrap.readthedocs.io
Project-URL: Repository, https://github.com/staticdev/django-sorting-bootstrap
